autotarget/autotarget.py
autotarget/init.py
autotarget/data/targets_inference_complete.csv
autotarget-1.0.0.3.dist-info/METADATA
autotarget-1.0.0.3.dist-info/WHEEL
autotarget-1.0.0.3.dist-info/top_level.txt
autotarget-1.0.0.3.dist-info/RECORD
